dictionary/__init__.py
dictionary/dictionary.py
erengazimutlu_cs453_HW1-2.3.4.dist-info/METADATA
erengazimutlu_cs453_HW1-2.3.4.dist-info/WHEEL
erengazimutlu_cs453_HW1-2.3.4.dist-info/top_level.txt
erengazimutlu_cs453_HW1-2.3.4.dist-info/RECORD
