Metadata-Version: 2.1
Name: erengazimutlu-cs453-HW1
Version: 2.3.4
Summary: UNKNOWN
Author: Erengazi Mutlu
License: UNKNOWN
Platform: UNKNOWN
Requires-Python: >=3.8
Requires-Dist: requests (>=2.23.0)
